[
    {
        "title": "Business Verification (KYB) on Camino Network",
        "description": "Today the team at Chain4Travel are happy to announce the beta launch of the Know Your Business (KYB) feature on the Camino Network.",
        "layout": "default",
        "author": "By Luca Cosivi",
        "date": "July 12th, 2023",
        "socialImage": "social-kyb ",
        "heroImage": "./src/static/images/_header/kyb-post.png"
    },
    {
        "title": "Business Verification (KYB) on Camino Network",
        "description": "Today the team at Chain4Travel are happy to announce the beta launch of the Know Your Business (KYB) feature on the Camino Network.",
        "layout": "default",
        "author": "By Luca Cosivi",
        "date": "July 12th, 2023",
        "socialImage": "social-kyb ",
        "heroImage": "./src/static/images/_header/kyb-post.png"
    },
    {
        "title": "Business Verification (KYB) on Camino Network",
        "description": "Today the team at Chain4Travel are happy to announce the beta launch of the Know Your Business (KYB) feature on the Camino Network.",
        "layout": "default",
        "author": "By Luca Cosivi",
        "date": "July 12th, 2023",
        "socialImage": "social-kyb ",
        "heroImage": "./src/static/images/_header/kyb-post.png"
    }
]